aijson_ml/__init__.py
aijson_ml/actions/__init__.py
aijson_ml/actions/fal.py
aijson_ml/actions/llm.py
aijson_ml/actions/transformer.py
aijson_ml/tests/__init__.py
aijson_ml/tests/conftest.py
aijson_ml/tests/test_llm.py
aijson_ml/tests/test_transformers.py
aijson_ml/utils/__init__.py
aijson_ml/utils/prompt_context.py
aijson_ml/utils/transformers_utils.py
aijson_ml-0.1.14.dist-info/LICENSE
aijson_ml-0.1.14.dist-info/METADATA
aijson_ml-0.1.14.dist-info/WHEEL
aijson_ml-0.1.14.dist-info/entry_points.txt
aijson_ml-0.1.14.dist-info/RECORD
